scraperex/__init__.py
scraperex/scraper.py
scraperex-0.0.14.dist-info/LICENSE
scraperex-0.0.14.dist-info/METADATA
scraperex-0.0.14.dist-info/WHEEL
scraperex-0.0.14.dist-info/top_level.txt
scraperex-0.0.14.dist-info/RECORD
