Metadata-Version: 2.1
Name: scraperex
Version: 0.0.14
Summary: Web scraper using dynamic proxy and user agent.
Home-page: https://github.com/userforce/scraper
Author: Tudor Corcimar
License: MIT
Keywords: scraper proxy user-agent
Platform: UNKNOWN
Classifier: Development Status :: 3 - Alpha
Classifier: Intended Audience :: Developers
Classifier: Topic :: Utilities
Classifier: License :: OSI Approved :: MIT License
Classifier: Programming Language :: Python :: 3.7
Requires-Python: >=3.7
Requires-Dist: requests
Requires-Dist: fake-useragent
